LICENSE
MANIFEST.in
README.rst
setup.py
bootstrap3_datetime/__init__.py
bootstrap3_datetime/widgets.py
bootstrap3_datetime.egg-info/PKG-INFO
bootstrap3_datetime.egg-info/SOURCES.txt
bootstrap3_datetime.egg-info/dependency_links.txt
bootstrap3_datetime.egg-info/top_level.txt
bootstrap3_datetime/static/bootstrap3_datetime/css/bootstrap-datetimepicker.min.css
bootstrap3_datetime/static/bootstrap3_datetime/js/bootstrap-datetimepicker.js
bootstrap3_datetime/static/bootstrap3_datetime/js/moment-with-locales.js
bootstrap3_datetime/static/bootstrap3_datetime/js/moment.min.js